delphi_utils/__init__.py
delphi_utils/__main__.py
delphi_utils/archive.py
delphi_utils/export.py
delphi_utils/geomap.py
delphi_utils/logger.py
delphi_utils/nancodes.py
delphi_utils/runner.py
delphi_utils/signal.py
delphi_utils/slack_notifier.py
delphi_utils/smooth.py
delphi_utils/utils.py
delphi_utils/weekday.py
delphi_utils/data/2019/chng-fips_state_table.csv
delphi_utils/data/2019/fips_chng-fips_table.csv
delphi_utils/data/2019/fips_hhs_table.csv
delphi_utils/data/2019/fips_hrr_table.csv
delphi_utils/data/2019/fips_msa_table.csv
delphi_utils/data/2019/fips_pop.csv
delphi_utils/data/2019/fips_state_table.csv
delphi_utils/data/2019/fips_zip_table.csv
delphi_utils/data/2019/hhs_pop.csv
delphi_utils/data/2019/nation_pop.csv
delphi_utils/data/2019/state_code_hhs_table.csv
delphi_utils/data/2019/state_codes_table.csv
delphi_utils/data/2019/state_pop.csv
delphi_utils/data/2019/zip_fips_table.csv
delphi_utils/data/2019/zip_hhs_table.csv
delphi_utils/data/2019/zip_hrr_table.csv
delphi_utils/data/2019/zip_hsa_table.csv
delphi_utils/data/2019/zip_msa_table.csv
delphi_utils/data/2019/zip_pop.csv
delphi_utils/data/2019/zip_state_code_table.csv
delphi_utils/data/2020/chng-fips_state_table.csv
delphi_utils/data/2020/fips_chng-fips_table.csv
delphi_utils/data/2020/fips_hhs_table.csv
delphi_utils/data/2020/fips_hrr_table.csv
delphi_utils/data/2020/fips_msa_table.csv
delphi_utils/data/2020/fips_pop.csv
delphi_utils/data/2020/fips_state_table.csv
delphi_utils/data/2020/fips_zip_table.csv
delphi_utils/data/2020/hhs_pop.csv
delphi_utils/data/2020/nation_pop.csv
delphi_utils/data/2020/state_code_hhs_table.csv
delphi_utils/data/2020/state_codes_table.csv
delphi_utils/data/2020/state_pop.csv
delphi_utils/data/2020/zip_fips_table.csv
delphi_utils/data/2020/zip_hhs_table.csv
delphi_utils/data/2020/zip_hrr_table.csv
delphi_utils/data/2020/zip_hsa_table.csv
delphi_utils/data/2020/zip_msa_table.csv
delphi_utils/data/2020/zip_pop.csv
delphi_utils/data/2020/zip_state_code_table.csv
delphi_utils-0.3.26.dist-info/LICENSE
delphi_utils-0.3.26.dist-info/METADATA
delphi_utils-0.3.26.dist-info/WHEEL
delphi_utils-0.3.26.dist-info/top_level.txt
delphi_utils-0.3.26.dist-info/RECORD
