Metadata-Version: 2.1
Name: delphi-utils
Version: 0.3.26
Summary: Shared Utility Functions for Indicators
License: MIT License
Project-URL: Homepage, https://github.com/cmu-delphi/covidcast-indicators
Classifier: Development Status :: 5 - Production/Stable
Classifier: Intended Audience :: Developers
Classifier: Programming Language :: Python :: 3.8
Classifier: License :: OSI Approved :: MIT License
Requires-Python: ==3.8.*
License-File: LICENSE
Requires-Dist: boto3
Requires-Dist: covidcast
Requires-Dist: cvxpy
Requires-Dist: epiweeks
Requires-Dist: gitpython
Requires-Dist: importlib-resources >=1.3
Requires-Dist: numpy
Requires-Dist: pyarrow
Requires-Dist: pandas >=1.1.0
Requires-Dist: requests
Requires-Dist: slackclient
Requires-Dist: scs <3.2.6
Requires-Dist: structlog
Requires-Dist: xlrd
Provides-Extra: dev
Requires-Dist: darker[isort] ~=2.1.1 ; extra == 'dev'
Requires-Dist: pylint ==2.8.3 ; extra == 'dev'
Requires-Dist: pytest ; extra == 'dev'
Requires-Dist: pydocstyle ; extra == 'dev'
Requires-Dist: pytest-cov ; extra == 'dev'
Requires-Dist: mock ; extra == 'dev'
Requires-Dist: moto ~=4.2.14 ; extra == 'dev'
Requires-Dist: requests-mock ; extra == 'dev'
Requires-Dist: freezegun ; extra == 'dev'
Provides-Extra: flash
Requires-Dist: scipy ; extra == 'flash'
